daemon/__init__.py
daemon/daemon.py
daemon/pidfile.py
python_daemon-3.1.0.dist-info/LICENSE.ASF-2
python_daemon-3.1.0.dist-info/LICENSE.GPL-3
python_daemon-3.1.0.dist-info/METADATA
python_daemon-3.1.0.dist-info/WHEEL
python_daemon-3.1.0.dist-info/top_level.txt
python_daemon-3.1.0.dist-info/RECORD
