Metadata-Version: 2.1
Name: python-daemon
Version: 3.1.0
Summary: Library to implement a well-behaved Unix daemon process.
Author-email: Ben Finney <ben+python@benfinney.id.au>
Maintainer: Ben Finney
Maintainer-email: ben+python@benfinney.id.au
License: Copying this work
Project-URL: Home Page, https://pagure.io/python-daemon/
Project-URL: Change Log, https://pagure.io/python-daemon/blob/main/f/ChangeLog
Project-URL: Source, https://pagure.io/python-daemon/
Project-URL: Issue Tracker, https://pagure.io/python-daemon/issues
Keywords: daemon,fork,unix
Classifier: Development Status :: 5 - Production/Stable
Classifier: License :: OSI Approved :: Apache Software License
Classifier: Operating System :: POSIX
Classifier: Programming Language :: Python :: 3
Classifier: Intended Audience :: Developers
Classifier: Topic :: Software Development :: Libraries :: Python Modules
Requires-Python: >=3.7
License-File: LICENSE.ASF-2
License-File: LICENSE.GPL-3
Requires-Dist: setuptools>=62.4.0
Requires-Dist: lockfile>=0.10
Provides-Extra: doc
Requires-Dist: Sphinx~=4.4; extra == "doc"
Provides-Extra: static-analysis
Requires-Dist: pip-check; extra == "static-analysis"
Requires-Dist: pycodestyle~=2.12; extra == "static-analysis"
Requires-Dist: pydocstyle~=6.3; extra == "static-analysis"
Requires-Dist: pyupgrade~=3.17; extra == "static-analysis"
Requires-Dist: isort~=5.13; extra == "static-analysis"
Provides-Extra: build
Requires-Dist: python-daemon[doc]; extra == "build"
Requires-Dist: wheel; extra == "build"
Requires-Dist: build; extra == "build"
Requires-Dist: docutils; extra == "build"
Requires-Dist: changelog-chug; extra == "build"
Provides-Extra: test
Requires-Dist: python-daemon[build,static-analysis]; extra == "test"
Requires-Dist: testtools; extra == "test"
Requires-Dist: testscenarios>=0.4; extra == "test"
Requires-Dist: coverage; extra == "test"
Provides-Extra: dist
Requires-Dist: python-daemon[build]; extra == "dist"
Requires-Dist: twine; extra == "dist"
Provides-Extra: devel
Requires-Dist: python-daemon[dist,test]; extra == "devel"
